README.md
setup.cfg
setup.py
datahandler_Ayush_101703130/__init__.py
datahandler_Ayush_101703130/basic.py
datahandler_Ayush_101703130/datahandler.py
datahandler_Ayush_101703130.egg-info/PKG-INFO
datahandler_Ayush_101703130.egg-info/SOURCES.txt
datahandler_Ayush_101703130.egg-info/dependency_links.txt
datahandler_Ayush_101703130.egg-info/top_level.txt