Metadata-Version: 2.1
Name: datahandler-Ayush-101703130
Version: 0.1
Summary: Handling Missing values in a given data set and imputing them.
Home-page: https://github.com/Ayushgupta03/datahandler
Author: Ayush/Ayush130
Author-email: guptayush0022@gmail.com
License: UNKNOWN
Download-URL: https://github.com/Ayushgupta03/datahandler/archive/v_01.tar.gz
Platform: UNKNOWN
Classifier: Programming Language :: Python :: 3
Classifier: License :: OSI Approved :: MIT License
Classifier: Operating System :: OS Independent
Requires-Python: >=3.6
